README.rst
_description.org
lh-agpl3-LICENSE.txt
pyproject.toml
setup.py
bin/bxoGitlab.py
bisos/__init__.py
bisos.bxoGitlab.egg-info/PKG-INFO
bisos.bxoGitlab.egg-info/SOURCES.txt
bisos.bxoGitlab.egg-info/dependency_links.txt
bisos.bxoGitlab.egg-info/not-zip-safe
bisos.bxoGitlab.egg-info/requires.txt
bisos.bxoGitlab.egg-info/top_level.txt
bisos/bxoGitlab/__init__.py