Metadata-Version: 2.2
Name: bisos.bxoGitlab
Version: 0.22
Summary: bisos.bxoGitlab: Python Command-Services for managing GIT repositories of BPO (BISOS Portable Objects) using the gitlab API.
Author: Mohsen Banan
Author-email: libre@mohsen.1.banan.byname.net
Maintainer: Mohsen Banan
Maintainer-email: libre@mohsen.1.banan.byname.net
License: AGPL
Classifier: Development Status :: 5 - Production/Stable
Classifier: Intended Audience :: Developers
Classifier: License :: OSI Approved :: GNU Affero General Public License v3
Classifier: Operating System :: POSIX
Classifier: Programming Language :: Python
Classifier: Topic :: Software Development :: Libraries
Classifier: Topic :: Software Development :: Libraries :: Python Modules
Requires-Dist: bisos
Requires-Dist: bisos.b
Requires-Dist: bisos.bxoGitlab
Requires-Dist: bisos.common
Requires-Dist: bisos.currents
Requires-Dist: bisos.examples
Requires-Dist: bisos.platform
Requires-Dist: bisos.transit
Requires-Dist: blee
Requires-Dist: blee.icmPlayer
Requires-Dist: certifi
Requires-Dist: charset-normalizer
Requires-Dist: enum34
Requires-Dist: idna
Requires-Dist: plumbum
Requires-Dist: python-gitlab
Requires-Dist: requests
Requires-Dist: requests-toolbelt
Requires-Dist: rpyc
Requires-Dist: unisos.icm
Requires-Dist: unisos.ucf
Requires-Dist: urllib3
Dynamic: author
Dynamic: author-email
Dynamic: classifier
Dynamic: description
Dynamic: license
Dynamic: maintainer
Dynamic: maintainer-email
Dynamic: requires-dist
Dynamic: summary
